pyjerasure/__init__.py
pyjerasure/__version__.py
pyjerasure/jerasure.cpython-39-darwin.so
pyjerasure/utils/__init__.py
pyjerasure-1.0.1.dist-info/LICENSE
pyjerasure-1.0.1.dist-info/METADATA
pyjerasure-1.0.1.dist-info/WHEEL
pyjerasure-1.0.1.dist-info/top_level.txt
pyjerasure-1.0.1.dist-info/RECORD
