Metadata-Version: 2.1
Name: pyjerasure
Version: 1.0.1
Summary: Python Wrapper for Jerasure
Home-page: https://github.com/ktnrg45/pyjerasure
Author: ktnrg45
Author-email: ktnrg45dev@gmail.com
License: Apache
Keywords: jerasure erasure erasures
Platform: UNKNOWN
Classifier: Development Status :: 4 - Beta
Classifier: License :: OSI Approved :: Apache Software License
Classifier: Natural Language :: English
Classifier: Operating System :: OS Independent
Classifier: Programming Language :: Python :: 3.8
Classifier: Topic :: Software Development :: Libraries :: Python Modules
Requires-Python: >=3.6
